gdrive_deploy/__init__.py
gdrive_deploy/__main__.py
gdrive_deploy/gdrive_deploy.py
gdrive_deploy/utilities.py
gdrive_deploy-1.0.2.dist-info/LICENSE
gdrive_deploy-1.0.2.dist-info/METADATA
gdrive_deploy-1.0.2.dist-info/WHEEL
gdrive_deploy-1.0.2.dist-info/entry_points.txt
gdrive_deploy-1.0.2.dist-info/top_level.txt
gdrive_deploy-1.0.2.dist-info/RECORD
